setup.py
distributions_pav/Binomialdistribution.py
distributions_pav/Gaussiandistribution.py
distributions_pav/Generaldistribution.py
distributions_pav/__init__.py
distributions_pav.egg-info/PKG-INFO
distributions_pav.egg-info/SOURCES.txt
distributions_pav.egg-info/dependency_links.txt
distributions_pav.egg-info/not-zip-safe
distributions_pav.egg-info/top_level.txt