Metadata-Version: 1.0
Name: distributions-pav
Version: 0.1
Summary: Gaussian and binomial distributions
Home-page: UNKNOWN
Author: Pavan
Author-email: UNKNOWN
License: UNKNOWN
Platform: UNKNOWN
